nanolog/__init__.py
nanolog/constants.py
nanolog/logger.py
nanolog/printing.py
nanolog-0.1.3.dist-info/DESCRIPTION.rst
nanolog-0.1.3.dist-info/METADATA
nanolog-0.1.3.dist-info/RECORD
nanolog-0.1.3.dist-info/WHEEL
nanolog-0.1.3.dist-info/entry_points.txt
nanolog-0.1.3.dist-info/metadata.json
nanolog-0.1.3.dist-info/top_level.txt
