Metadata-Version: 2.0
Name: nanolog
Version: 0.1.3
Summary: python logging on steroids, lightweight and convenient
Home-page: http://github.com/SurrealAI/nanolog
Author: Jim Fan
Author-email: UNKNOWN
License: GPLv3
Keywords: logging,utility
Platform: UNKNOWN
Classifier: Development Status :: 4 - Beta
Classifier: Environment :: Console
Classifier: Programming Language :: Python :: 3
Requires-Python: >=3.0
Requires-Dist: prettyprinter
